marinedebrisdetector/__init__.py
marinedebrisdetector/callbacks.py
marinedebrisdetector/checkpoints.py
marinedebrisdetector/main_cli.py
marinedebrisdetector/metrics.py
marinedebrisdetector/predictor.py
marinedebrisdetector/test.py
marinedebrisdetector/train.py
marinedebrisdetector/transforms.py
marinedebrisdetector/visualization.py
marinedebrisdetector/data/__init__.py
marinedebrisdetector/data/durban.py
marinedebrisdetector/data/floatingobjects.py
marinedebrisdetector/data/label_refinement.py
marinedebrisdetector/data/marida.py
marinedebrisdetector/data/marinedebrisdatamodule.py
marinedebrisdetector/data/plastic_litter_project.py
marinedebrisdetector/data/refined_floatingobjects.py
marinedebrisdetector/data/s2ships.py
marinedebrisdetector/data/utils.py
marinedebrisdetector/model/__init__.py
marinedebrisdetector/model/model.py
marinedebrisdetector/model/segmentation_model.py
marinedebrisdetector/model/unet.py
marinedebrisdetector/model/random_forest/__init__.py
marinedebrisdetector/model/random_forest/engineering_patches.py
marinedebrisdetector/model/random_forest/main_qualitative.py
marinedebrisdetector/model/random_forest/random_forest.py
marinedebrisdetector/model/random_forest/readme.md
marinedebrisdetector-0.0.2.dist-info/METADATA
marinedebrisdetector-0.0.2.dist-info/WHEEL
marinedebrisdetector-0.0.2.dist-info/entry_points.txt
marinedebrisdetector-0.0.2.dist-info/licenses/LICENSE
marinedebrisdetector-0.0.2.dist-info/RECORD
