Metadata-Version: 2.1
Name: marinedebrisdetector
Version: 0.0.2
Summary: A detector of marine debris with Sentinel-2 scenes
Project-URL: Homepage, https://github.com/marccoru/marinedebrisdetector
Author-email: Marc Russwurm <marc.russwurm@epfl.ch>
License-File: LICENSE
Classifier: License :: OSI Approved :: MIT License
Classifier: Operating System :: OS Independent
Classifier: Programming Language :: Python :: 3
Requires-Python: >=3.7
Requires-Dist: einops
Requires-Dist: geopandas
Requires-Dist: matplotlib
Requires-Dist: numpy
Requires-Dist: pandas
Requires-Dist: pytorch-lightning
Requires-Dist: rasterio
Requires-Dist: scikit-image
Requires-Dist: scikit-learn
Requires-Dist: segmentation-models-pytorch
Requires-Dist: shapely
Requires-Dist: torch
Requires-Dist: torchvision
Requires-Dist: tqdm
Requires-Dist: wandb
